{"index":21,"name":"Spearow","size":"Tiny","SR":0.25,"MIN LVL FD":1,"Type":["Normal","Flying"],"Abilities":["Keen Eye"],"Hidden Ability":"Sniper","WSp":10,"Fsp":25,"Ssp":0,"Climbing Speed":0,"Burrowing Speed":0,"AC":12,"HP":16,"Hit Dice":6,"attributes":{"STR":10,"DEX":14,"CON":10,"INT":6,"WIS":10,"CHA":10},"Moves":{"Level":{"10":["Assurance","Agility"],"14":["Focus Energy","Roost"],"18":["Drill Peck"],"2":["Pursuit","Fury Attack"],"6":["Aerial Ace","Mirror Move"]},"Starting Moves":["Growl","Peck","Leer"],"TM":[1,6,10,11,17,18,19,21,27,32,40,42,44,45,46,48,49,51,54,76,87,88,89,90,100],"egg":["Astonish","Feint Attack","False Swipe","Feather Dance","Quick Attack","Razor Wind","Scary Face","Sky Attack","Tri Attack","Uproar","Whirlwind"]},"saving_throws":["Dexterity"],"Skill":["Perception"],"Evolve":{"into":["Fearow"],"requires":[],"current_stage":1,"total_stages":2,"points":9,"level":6,"move":null}}