{"index":236,"name":"Tyrogue","size":"Small","SR":0.25,"MIN LVL FD":1,"Type":["Fighting"],"Abilities":["Guts","Steadfast"],"Hidden Ability":"Vital Spirit","WSp":25,"Fsp":0,"Ssp":0,"Climbing Speed":0,"Burrowing Speed":0,"AC":11,"HP":17,"Hit Dice":6,"attributes":{"STR":12,"DEX":12,"CON":12,"INT":6,"WIS":10,"CHA":10},"Moves":{"Level":{},"Starting Moves":["Fake Out","Foresight","Helping Hand","Tackle"],"TM":[1,6,8,10,11,17,18,21,26,27,31,32,42,44,45,46,47,48,78,80,87,88,90,100],"egg":["Bullet Punch","Counter","Endure","Feint","Helping Hand","Mach Punch","Mind Reader","Pursuit","Rapid Spin","Vacuum Wave"]},"saving_throws":["Dexterity"],"Skill":["Acrobatics"],"Evolve":{"into":["Hitmonlee","Hitmonchan","Hitmontop"],"requires":["Dex \u003E Str","Str \u003E Dex","Str = Dex"],"current_stage":1,"total_stages":2,"points":8,"level":6,"move":null}}