{"index":25,"name":"Pikachu","size":"Tiny","SR":0.5,"MIN LVL FD":1,"Type":["Electric"],"Abilities":["Static"],"Hidden Ability":"Lightning Rod","WSp":30,"Fsp":0,"Ssp":0,"Climbing Speed":0,"Burrowing Speed":0,"AC":13,"HP":16,"Hit Dice":6,"attributes":{"STR":11,"DEX":15,"CON":10,"INT":6,"WIS":10,"CHA":12},"Moves":{"Level":{"10":["Double Team","Spark","Discharge","Nuzzle"],"14":["Slam","Thunderbolt","Agility"],"18":["Wild Charge","Light Screen","Thunder"],"2":["Growl","Quick Attack","Play Nice"],"6":["Electro Ball","Thunder Wave","Feint"]},"Starting Moves":["Tail Whip","Thunder Shock","Play Nice"],"TM":[6,10,16,17,18,21,24,25,27,31,32,42,44,45,48,49,56,57,72,73,86,87,88,90,93,100],"egg":[]},"saving_throws":["Dexterity","Charisma"],"Skill":["Acrobatics","Persuasion"],"Evolve":{"into":["Raichu","Alolan Raichu"],"requires":["Thunder stone","Alola Stone"],"current_stage":2,"total_stages":3,"points":9,"level":8,"move":null}}