{"index":476,"name":"Probopass","size":"Medium","SR":13,"MIN LVL FD":8,"Type":["Rock","Steel"],"Abilities":["Sturdy","Magnet Pull"],"Hidden Ability":"Sand Force","WSp":25,"Fsp":25,"Ssp":0,"Climbing Speed":0,"Burrowing Speed":0,"AC":20,"HP":97,"Hit Dice":12,"attributes":{"STR":20,"DEX":12,"CON":19,"INT":6,"WIS":12,"CHA":10},"Moves":{"Level":{"10":["Power Gem","Rock Blast","Discharge"],"14":["Sandstorm","Earth Power","Stone Edge"],"18":["Lock-On","Zap Cannon"]},"Starting Moves":["Block","Gravity","Iron Defense","Magnet Bomb","Magnet Rise","Tackle","Tri Attack","Wide Guard","Thunder Wave","Rest","Spark","Rock Slide","Magnetic Flux"],"TM":[6,10,11,12,15,17,21,23,24,25,26,27,32,37,39,41,42,44,45,48,64,68,69,71,72,73,78,80,87,88,90,91,99,100],"egg":[]},"saving_throws":["Strength","Constitution"],"Skill":["Survival"],"Evolve":null}